Metadata-Version: 1.0
Name: getchforpython
Version: 0.0
Summary: Getch For Python 3
Home-page: UNKNOWN
Author: UNKNOWN
Author-email: alexanderbrehov36@gmail.com
License: UNKNOWN
Platform: UNKNOWN
